CHANGES.txt
CONTRIBUTORS.txt
MANIFEST.in
README.rst
bootstrap-buildout.py
setup.cfg
setup.py
varnish.cfg
versions.cfg
docs/LICENSE.GPL
docs/LICENSE.txt
docs/README.rst
docs/source/end-user.rst
docs/source/index.rst
docs/source/installation.rst
docs/source/images/SS1.png
docs/source/images/SS2.png
docs/source/images/SS3.png
docs/source/images/SS4.png
src/collective/__init__.py
src/collective.jekyll.egg-info/PKG-INFO
src/collective.jekyll.egg-info/SOURCES.txt
src/collective.jekyll.egg-info/dependency_links.txt
src/collective.jekyll.egg-info/namespace_packages.txt
src/collective.jekyll.egg-info/not-zip-safe
src/collective.jekyll.egg-info/requires.txt
src/collective.jekyll.egg-info/top_level.txt
src/collective/jekyll/__init__.py
src/collective/jekyll/configure.zcml
src/collective/jekyll/diagnosis.py
src/collective/jekyll/ignored.py
src/collective/jekyll/interfaces.py
src/collective/jekyll/setuphandlers.py
src/collective/jekyll/symptoms.py
src/collective/jekyll/testing.py
src/collective/jekyll/testing.zcml
src/collective/jekyll/browser/__init__.py
src/collective/jekyll/browser/collection_view.pt
src/collective/jekyll/browser/configure.zcml
src/collective/jekyll/browser/controlpanel.py
src/collective/jekyll/browser/detailed.pt
src/collective/jekyll/browser/diagnosis.py
src/collective/jekyll/browser/diagnosis_status.pt
src/collective/jekyll/browser/filter.py
src/collective/jekyll/browser/icon.png
src/collective/jekyll/browser/interfaces.py
src/collective/jekyll/browser/symptom.pt
src/collective/jekyll/browser/symptom_status.pt
src/collective/jekyll/browser/viewlet.pt
src/collective/jekyll/browser/static/diagnosis.css
src/collective/jekyll/browser/static/toggle.js
src/collective/jekyll/locales/collective.jekyll.pot
src/collective/jekyll/locales/en/LC_MESSAGES/collective.jekyll.po
src/collective/jekyll/locales/fr/LC_MESSAGES/collective.jekyll.po
src/collective/jekyll/locales/it/LC_MESSAGES/collective.jekyll.po
src/collective/jekyll/locales/nl/LC_MESSAGES/collective.jekyll.po
src/collective/jekyll/profiles/default/browserlayer.xml
src/collective/jekyll/profiles/default/collective_jekyll_various.txt
src/collective/jekyll/profiles/default/controlpanel.xml
src/collective/jekyll/profiles/default/cssregistry.xml
src/collective/jekyll/profiles/default/import_steps.xml
