Metadata-Version: 1.1
Name: collective.jekyll
Version: 0.4.0
Summary: Diagnostic for your Plone content
Home-page: http://svn.plone.org/svn/collective/
Author: Godefroid Chapelle
Author-email: gotcha@bubblenet.be
License: gpl
Keywords: Plone content diagnosis
Platform: UNKNOWN
Classifier: Programming Language :: Python
Classifier: Programming Language :: Python :: 2.6
Classifier: Programming Language :: Python :: 2.7
